cqmseeker/__init__.py
cqmseeker/cqmseeker.cpython-311-windows.pyd
cqmseeker/cqmseeker.py
cqmseeker/highs.dll
cqmseeker/libboost_filesystem-mt.dll
cqmseeker/libstdc++-6.dll
cqmseeker/libwinpthread-1.dll
cqmseeker/seeker.dll
cqmseeker/bin/coll.exe
cqmseeker/bin/hard.exe
cqmseeker/scripts/collect.sh
cqmseeker/scripts/seekeragg.sh
cqmseeker-0.0.5.dist-info/AUTHORS.rst
cqmseeker-0.0.5.dist-info/LICENSE.rst
cqmseeker-0.0.5.dist-info/METADATA
cqmseeker-0.0.5.dist-info/WHEEL
cqmseeker-0.0.5.dist-info/top_level.txt
cqmseeker-0.0.5.dist-info/RECORD
